git_dependency_python/__init__.py
git_dependency_python/dependency_lock_manager.py
git_dependency_python/dependency_manager.py
git_dependency_python/git_dependency.py
git_dependency_python/pip_helper.py
git_dependency_python/setup_helper.py
git_dependency_python/tools.py
git_dependency_python/version_resolver.py
git_dependency_python-1.1.2.dist-info/LICENSE.txt
git_dependency_python-1.1.2.dist-info/METADATA
git_dependency_python-1.1.2.dist-info/WHEEL
git_dependency_python-1.1.2.dist-info/top_level.txt
git_dependency_python-1.1.2.dist-info/RECORD
